ml4floods/__init__.py
ml4floods/data/S2_SAFE_reader.py
ml4floods/data/__init__.py
ml4floods/data/cmcloudsen12.py
ml4floods/data/cmkappazeta.py
ml4floods/data/cms2cloudless.py
ml4floods/data/config.py
ml4floods/data/create_gt.py
ml4floods/data/dataset.py
ml4floods/data/ee_download.py
ml4floods/data/save_cog.py
ml4floods/data/utils.py
ml4floods/data/vectorize.py
ml4floods/data/configuration/train_test_split_extra_dataset.json
ml4floods/data/configuration/train_test_split_original_dataset.json
ml4floods/data/copernicusEMS/__init__.py
ml4floods/data/copernicusEMS/activations.py
ml4floods/data/copernicusEMS/utils.py
ml4floods/data/index/__init__.py
ml4floods/data/index/geographic_index.py
ml4floods/data/index/indexer.py
ml4floods/data/index/indexer_arg_parser.py
ml4floods/data/index/map_data.py
ml4floods/data/index/map_data_factory.py
ml4floods/data/unosat/__init__.py
ml4floods/data/unosat/unosat_download.py
ml4floods/data/unosat/unosat_download_arg_parser.py
ml4floods/data/worldfloods/__init__.py
ml4floods/data/worldfloods/configs.py
ml4floods/data/worldfloods/create_worldfloods_dataset.py
ml4floods/data/worldfloods/dataset.py
ml4floods/data/worldfloods/download.py
ml4floods/data/worldfloods/lightning.py
ml4floods/models/__init__.py
ml4floods/models/config_setup.py
ml4floods/models/dataset_setup.py
ml4floods/models/model_setup.py
ml4floods/models/postprocess.py
ml4floods/models/worldfloods_model.py
ml4floods/models/architectures/__init__.py
ml4floods/models/architectures/baselines.py
ml4floods/models/architectures/hrnet_seg.py
ml4floods/models/architectures/layer_factory.py
ml4floods/models/architectures/ndwi.py
ml4floods/models/architectures/unets.py
ml4floods/models/configurations/__init__.py
ml4floods/models/configurations/worldfloods_template.json
ml4floods/models/configurations/worldfloods_template_v2.json
ml4floods/models/configurations/worldfloods_uncertainty.json
ml4floods/models/utils/__init__.py
ml4floods/models/utils/configuration.py
ml4floods-1.1.1.dist-info/LICENSE
ml4floods-1.1.1.dist-info/METADATA
ml4floods-1.1.1.dist-info/WHEEL
ml4floods-1.1.1.dist-info/top_level.txt
ml4floods-1.1.1.dist-info/RECORD
