Metadata-Version: 2.1
Name: ml4floods
Version: 1.1.1
Summary: Machine learning models for end-to-end flood extent segmentation.
Home-page: https://github.com/spaceml-org/ml4floods
Author: SpaceML-org
Keywords: floods pytorch machine-learning earth
Classifier: Programming Language :: Python :: 3.10
Classifier: License :: OSI Approved :: GNU Lesser General Public License v3 (LGPLv3)
Classifier: Operating System :: OS Independent
Classifier: Intended Audience :: Science/Research
Classifier: Natural Language :: English
Classifier: Topic :: Scientific/Engineering :: GIS
Classifier: Development Status :: 5 - Production/Stable
License-File: LICENSE
Requires-Dist: torch
Requires-Dist: torchvision
Requires-Dist: pytorch-lightning
Requires-Dist: numpy
Requires-Dist: matplotlib
Requires-Dist: pandas
Requires-Dist: rasterio
Requires-Dist: geopandas
Requires-Dist: tqdm
Requires-Dist: albumentations
Requires-Dist: google-cloud-storage
Requires-Dist: fsspec
Requires-Dist: gcsfs
Requires-Dist: requests-html
Requires-Dist: earthengine-api
Requires-Dist: mercantile
Requires-Dist: seaborn
Requires-Dist: gdown
Requires-Dist: matplotlib-scalebar
Requires-Dist: georeader-spaceml
Requires-Dist: huggingface-hub[cli,torch]
Provides-Extra: dev
Requires-Dist: black ; extra == 'dev'
Requires-Dist: isort ; extra == 'dev'
Requires-Dist: pylint ; extra == 'dev'
Requires-Dist: flake8 ; extra == 'dev'
Requires-Dist: pyprojroot ; extra == 'dev'
Provides-Extra: docs
Requires-Dist: furo ==2020.12.30b24 ; extra == 'docs'
Requires-Dist: nbsphinx ==0.8.1 ; extra == 'docs'
Requires-Dist: nb-black ==1.0.7 ; extra == 'docs'
Requires-Dist: matplotlib ==3.3.3 ; extra == 'docs'
Requires-Dist: sphinx-copybutton ==0.3.1 ; extra == 'docs'
Provides-Extra: tests
Requires-Dist: pytest ; extra == 'tests'
